lindi/LindiH5ZarrStore/LindiH5ZarrStore.py
lindi/LindiH5ZarrStore/LindiH5ZarrStoreOpts.py
lindi/LindiH5ZarrStore/__init__.py
lindi/LindiH5ZarrStore/_util.py
lindi/LindiH5pyFile/LindiH5pyAttributes.py
lindi/LindiH5pyFile/LindiH5pyDataset.py
lindi/LindiH5pyFile/LindiH5pyFile.py
lindi/LindiH5pyFile/LindiH5pyGroup.py
lindi/LindiH5pyFile/LindiH5pyLink.py
lindi/LindiH5pyFile/LindiH5pyReference.py
lindi/LindiH5pyFile/LindiReferenceFileSystemStore.py
lindi/LindiH5pyFile/__init__.py
lindi/LindiH5pyFile/writers/LindiH5pyAttributesWriter.py
lindi/LindiH5pyFile/writers/LindiH5pyDatasetWriter.py
lindi/LindiH5pyFile/writers/LindiH5pyGroupWriter.py
lindi/LindiH5pyFile/writers/__init__.py
lindi/LindiRemfile/LindiRemfile.py
lindi/LindiRemfile/__init__.py
lindi/LindiRemfile/additional_url_resolvers.py
lindi/LocalCache/LocalCache.py
lindi/LocalCache/__init__.py
lindi/__init__.py
lindi/conversion/__init__.py
lindi/conversion/_util.py
lindi/conversion/attr_conversion.py
lindi/conversion/create_zarr_dataset_from_h5_data.py
lindi/conversion/decode_references.py
lindi/conversion/h5_filters_to_codecs.py
lindi/conversion/h5_ref_to_zarr_attr.py
lindi/conversion/nan_inf_ninf.py
lindi/conversion/reformat_json.py
lindi/tar/LindiTarStore.py
lindi/tar/create_tar_header.py
lindi/tar/lindi_tar.py
lindi-0.4.5.dist-info/LICENSE
lindi-0.4.5.dist-info/METADATA
lindi-0.4.5.dist-info/WHEEL
lindi-0.4.5.dist-info/RECORD
