Metadata-Version: 2.3
Name: lindi
Version: 0.4.5
Summary: 
Author: Jeremy Magland
Author-email: jmagland@flatironinstitute.org
Requires-Python: >=3.8
Classifier: Programming Language :: Python :: 3
Classifier: Programming Language :: Python :: 3.8
Classifier: Programming Language :: Python :: 3.9
Classifier: Programming Language :: Python :: 3.10
Classifier: Programming Language :: Python :: 3.11
Classifier: Programming Language :: Python :: 3.12
Classifier: Programming Language :: Python :: 3.13
Requires-Dist: h5py (>=3.10.0,<4.0.0)
Requires-Dist: numcodecs (>=0.11.0)
Requires-Dist: requests (>=2.31.0,<3.0.0)
Requires-Dist: tqdm (>=4.66.4,<5.0.0)
Requires-Dist: zarr (>=2.16.1,<3.0.0)
